xdriver/__init__.py
xdriver/src/__init__.py
xdriver/src/webdriver.py
xdriver-1.2.3.dist-info/LICENSE
xdriver-1.2.3.dist-info/METADATA
xdriver-1.2.3.dist-info/WHEEL
xdriver-1.2.3.dist-info/top_level.txt
xdriver-1.2.3.dist-info/RECORD
