Metadata-Version: 2.1
Name: xdriver
Version: 1.2.3
Summary: Expanded Selenium WebDriver
Home-page: https://github.com/rokasbarvainisgit/xdriver.git
License: MIT
Classifier: Programming Language :: Python
Classifier: Programming Language :: Python :: 3.10
Classifier: Programming Language :: Python :: 3.11
Classifier: Programming Language :: Python :: 3.12
Classifier: Programming Language :: Python :: 3.13
Classifier: License :: OSI Approved :: MIT License
Classifier: Operating System :: OS Independent
Requires-Python: >=3.10
License-File: LICENSE
Requires-Dist: pytest~=8.3.2
Requires-Dist: selenium~=4.23.1
